napari_mahotas_image_processing/__init__.py
napari_mahotas_image_processing/_function.py
napari_mahotas_image_processing/_tests/__init__.py
napari_mahotas_image_processing/_tests/test_function.py
napari_mahotas_image_processing-0.1.3.dist-info/LICENSE
napari_mahotas_image_processing-0.1.3.dist-info/METADATA
napari_mahotas_image_processing-0.1.3.dist-info/WHEEL
napari_mahotas_image_processing-0.1.3.dist-info/entry_points.txt
napari_mahotas_image_processing-0.1.3.dist-info/licenses_thirdparty.txt
napari_mahotas_image_processing-0.1.3.dist-info/top_level.txt
napari_mahotas_image_processing-0.1.3.dist-info/RECORD
