Metadata-Version: 2.1
Name: napari-mahotas-image-processing
Version: 0.1.3
Summary: Image processing based using the Mahotas library in napari
Home-page: https://github.com/haesleinhuepf/napari-mahotas-image-processing
Author: Robert Haase
Author-email: robert.haase@tu-dresden.de
License: BSD-3-Clause
Project-URL: Bug Tracker, https://github.com/haesleinhuepf/napari-mahotas-image-processing/issues
Project-URL: Documentation, https://github.com/haesleinhuepf/napari-mahotas-image-processing#README.md
Project-URL: Source Code, https://github.com/haesleinhuepf/napari-mahotas-image-processing
Project-URL: User Support, https://github.com/haesleinhuepf/napari-mahotas-image-processing/issues
Platform: UNKNOWN
Classifier: Development Status :: 2 - Pre-Alpha
Classifier: Intended Audience :: Science/Research
Classifier: Topic :: Scientific/Engineering :: Image Processing
Classifier: Programming Language :: Python
Classifier: Programming Language :: Python :: 3
Classifier: Programming Language :: Python :: 3.7
Classifier: Programming Language :: Python :: 3.8
Classifier: Programming Language :: Python :: 3.9
Classifier: Operating System :: OS Independent
Classifier: License :: OSI Approved :: BSD License
Requires-Python: >=3.7
License-File: LICENSE
License-File: licenses_thirdparty.txt
Requires-Dist: napari-plugin-engine (>=0.1.4)
Requires-Dist: numpy
Requires-Dist: mahotas
Requires-Dist: napari-time-slicer
Requires-Dist: napari-tools-menu (>=0.4.2)
